autoimgrenamer/__init__.py
autoimgrenamer/autoimgrenamer.py
autoimgrenamer-0.1.1.dist-info/License
autoimgrenamer-0.1.1.dist-info/METADATA
autoimgrenamer-0.1.1.dist-info/WHEEL
autoimgrenamer-0.1.1.dist-info/top_level.txt
autoimgrenamer-0.1.1.dist-info/RECORD
