Metadata-Version: 2.1
Name: autoimgrenamer
Version: 0.1.1
Summary: A simple tool to rename image files in a folder.
Author: Md. Ismiel Hossen Abir
Author-email: ismielabir1971@gmail.com
Classifier: Programming Language :: Python :: 3
Classifier: License :: OSI Approved :: MIT License
Classifier: Operating System :: OS Independent
License-File: License
